twirl/__init__.py
twirl/cli.py
twirldata-0.0.0.dist-info/METADATA
twirldata-0.0.0.dist-info/WHEEL
twirldata-0.0.0.dist-info/entry_points.txt
twirldata-0.0.0.dist-info/top_level.txt
twirldata-0.0.0.dist-info/RECORD
