Metadata-Version: 2.1
Name: twirldata
Version: 0.0.0
Summary: Client SDK for the Twirl data platform
Author-email: Twirl Data <hello@twirldata.com>
Project-URL: Homepage, https://twirldata.com
Classifier: Development Status :: 3 - Alpha
Classifier: Environment :: Console
Classifier: Environment :: Web Environment
Classifier: Intended Audience :: Developers
Classifier: Operating System :: OS Independent
Classifier: Programming Language :: Python :: 3
Classifier: Topic :: Software Development :: Libraries :: Application Frameworks
Requires-Python: >=3.9
